monocle_mainbanner-0.1.5.dist-info/RECORD
monocle_mainbanner-0.1.5.dist-info/top_level.txt
monocle_mainbanner-0.1.5.dist-info/DESCRIPTION.rst
monocle_mainbanner-0.1.5.dist-info/METADATA
monocle_mainbanner-0.1.5.dist-info/metadata.json
monocle_mainbanner-0.1.5.dist-info/WHEEL
monocle_mainbanner/models.py
monocle_mainbanner/monocle.py
monocle_mainbanner/__init__.py
monocle_mainbanner/admin.py
monocle_mainbanner/images_readme/mainbanner_admin.png
monocle_mainbanner/images_readme/mainbanner.png
monocle_mainbanner/templates/monocle_mainbanner/monocle_mainbanner.html
monocle_mainbanner/fixtures/monocle_mainbanner.json
monocle_mainbanner/fixtures/monocle_mainbanner/banner_2.jpg
monocle_mainbanner/fixtures/monocle_mainbanner/Chrysanthemum.jpg
monocle_mainbanner/fixtures/monocle_mainbanner/Lighthouse.jpg
monocle_mainbanner/fixtures/monocle_mainbanner/сighthouse.jpg
monocle_mainbanner/fixtures/monocle_mainbanner/chrysanthemum.jpg
monocle_mainbanner/fixtures/monocle_mainbanner/banner_1.jpg
monocle_mainbanner/fixtures/monocle_mainbanner/banner_3.jpg
monocle_mainbanner/fixtures/monocle_mainbanner/сhrysanthemum.jpg
monocle_mainbanner/static/monocle_mainbanner/monocle_mainbanner.js
monocle_mainbanner/static/monocle_mainbanner/monocle_mainbanner.css
